debauto/__init__.py
debauto/remessa.py
debauto/retorno.py
debauto/utils.py
debauto/bancos/__init__.py
debauto/bancos/bb.py
debauto/bancos/caixa.py
debauto/bancos/santander.py
python_debauto_br-0.2.2.dist-info/LICENSE.md
python_debauto_br-0.2.2.dist-info/METADATA
python_debauto_br-0.2.2.dist-info/WHEEL
python_debauto_br-0.2.2.dist-info/top_level.txt
python_debauto_br-0.2.2.dist-info/RECORD
