Metadata-Version: 2.1
Name: python-debauto-br
Version: 0.2.2
Summary: Criação de remessas de débito automático no formato CNAB 150 da Febraban.
Home-page: https://github.com/flaviomilan/python-debauto-br
Author: Flavio Milan
Author-email: flaviomilan@outlook.com
License: MIT
Platform: UNKNOWN
Classifier: License :: OSI Approved :: MIT License
Classifier: Programming Language :: Python
Classifier: Programming Language :: Python :: 2.7
Classifier: Programming Language :: Python :: 3.5
Classifier: Programming Language :: Python :: 3.6
Classifier: Programming Language :: Python :: 3.7
Classifier: Programming Language :: Python :: Implementation :: CPython
Requires-Python: >=3.5.0
Provides-Extra: fancy_feature
Requires-Dist: django ; extra == 'fancy_feature'
